regli/__init__.py
regli/ezmcmc.py
regli/mcmc.py
regli/regli.py
regli/regress.py
regli/spin.py
regli-2023.829.0.dist-info/LICENSE
regli-2023.829.0.dist-info/METADATA
regli-2023.829.0.dist-info/WHEEL
regli-2023.829.0.dist-info/top_level.txt
regli-2023.829.0.dist-info/RECORD
