Metadata-Version: 2.1
Name: regli
Version: 2023.829.0
Summary: REgular Grid Linear Interpolator.
Home-page: http://github.com/hypergravity/regli
Author: Bo Zhang
Author-email: bozhang@nao.cas.cn
License: MIT
Classifier: Development Status :: 5 - Production/Stable
Classifier: Intended Audience :: Science/Research
Classifier: License :: OSI Approved :: MIT License
Classifier: Operating System :: OS Independent
Classifier: Programming Language :: Python :: 3.7
Classifier: Topic :: Scientific/Engineering :: Physics
Classifier: Topic :: Scientific/Engineering :: Astronomy
Requires: numpy
Requires: scipy
Requires: emcee
Requires: astroslam
Requires: joblib
Requires: laspec
License-File: LICENSE
